seg_metrics/__init__.py
seg_metrics/seg_metrics.py
tests/__init__.py
tests/runner.py
tests/test_save_and_load_itk.py
tests/test_spacing.py
tests/test_tptnfpfn.py
tests/test_type_check.py
tests/test_write_metrics_itk_or_array.py
seg_metrics-1.2.8.dist-info/LICENSE
seg_metrics-1.2.8.dist-info/METADATA
seg_metrics-1.2.8.dist-info/WHEEL
seg_metrics-1.2.8.dist-info/top_level.txt
seg_metrics-1.2.8.dist-info/RECORD
