Metadata-Version: 2.1
Name: seg_metrics
Version: 1.2.8
Summary: A package to compute different segmentation metrics for 2D/3D medical images.
Home-page: https://github.com/Ordgod/segmentation_metrics
Author: Jingnan Jia
Author-email: jiajingnan2222@gmail.com
Classifier: Programming Language :: Python :: 3
Classifier: License :: OSI Approved :: MIT License
Classifier: Operating System :: OS Independent
Requires-Python: >=3.6
License-File: LICENSE
Requires-Dist: pandas
Requires-Dist: numpy
Requires-Dist: coverage
Requires-Dist: matplotlib
Requires-Dist: parameterized
Requires-Dist: tqdm
Requires-Dist: medutils
Requires-Dist: PySimpleGUI
Requires-Dist: SimpleITK
